cnpj_mcp_server/__init__.py
cnpj_mcp_server/server.py
buscador_de_cnpj-0.2.8.dist-info/METADATA
buscador_de_cnpj-0.2.8.dist-info/WHEEL
buscador_de_cnpj-0.2.8.dist-info/entry_points.txt
buscador_de_cnpj-0.2.8.dist-info/licenses/LICENSE
buscador_de_cnpj-0.2.8.dist-info/RECORD
