Metadata-Version: 2.4
Name: buscador-de-cnpj
Version: 0.2.8
Summary: A MCP server for CNPJ search using buscadordecnpj.com API
Project-URL: Homepage, https://github.com/victortavernari/cnpj-mcp-server
Project-URL: Repository, https://github.com/victortavernari/cnpj-mcp-server
Project-URL: Issues, https://github.com/victortavernari/cnpj-mcp-server/issues
Project-URL: Documentation, https://github.com/victortavernari/cnpj-mcp-server#readme
Author-email: Buscador de CNPJ <contato@buscadordecnpj.com>
License: MIT
License-File: LICENSE
Keywords: api,brazil,cnpj,company,mcp,search
Classifier: Development Status :: 4 - Beta
Classifier: Intended Audience :: Developers
Classifier: License :: OSI Approved :: MIT License
Classifier: Operating System :: OS Independent
Classifier: Programming Language :: Python :: 3
Classifier: Programming Language :: Python :: 3.11
Classifier: Programming Language :: Python :: 3.12
Classifier: Topic :: Internet :: WWW/HTTP :: HTTP Servers
Classifier: Topic :: Software Development :: Libraries :: Python Modules
Requires-Python: >=3.11
Requires-Dist: aiohttp>=3.11.16
Requires-Dist: certifi>=2025.1.31
Requires-Dist: mcp[cli]>=1.6.0
Requires-Dist: pydantic>=2.11.2
Requires-Dist: python-dotenv>=1.1.0
